{
  "topalbums": {
    "album": [
      {
        "name": "Nymphetamine",
        "playcount": 4380662,
        "mbid": "b7bea46d-8986-363c-8f81-458b81e8944b",
        "url": "https://www.last.fm/music/Cradle+of+Filth/Nymphetamine",
        "artist": {
          "name": "Cradle of Filth",
          "mbid": "7e26cbe1-b8f5-4215-af82-e43d5f8ff308",
          "url": "https://www.last.fm/music/Cradle+of+Filth"
        },
        "image": [
          {
            "#text": "https://lastfm.freetls.fastly.net/i/u/34s/67f4308c12b14445b21b13cc7b7fd675.png",
            "size": "small"
          },
          {
            "#text": "https://lastfm.freetls.fastly.net/i/u/64s/67f4308c12b14445b21b13cc7b7fd675.png",
            "size": "medium"
          },
          {
            "#text": "https://lastfm.freetls.fastly.net/i/u/174s/67f4308c12b14445b21b13cc7b7fd675.png",
            "size": "large"
          },
          {
            "#text": "https://lastfm.freetls.fastly.net/i/u/300x300/67f4308c12b14445b21b13cc7b7fd675.png",
            "size": "extralarge"
          }
        ]
      },
      {
        "name": "Midian",
        "playcount": 3081202,
        "mbid": "78a9253e-0fbc-4aff-ade7-774da2756eb2",
        "url": "https://www.last.fm/music/Cradle+of+Filth/Midian",
        "artist": {
          "name": "Cradle of Filth",
          "mbid": "7e26cbe1-b8f5-4215-af82-e43d5f8ff308",
          "url": "https://www.last.fm/music/Cradle+of+Filth"
        },
        "image": [
          {
            "#text": "https://lastfm.freetls.fastly.net/i/u/34s/80851305d15888d28074fe9a3eba851d.png",
            "size": "small"
          },
          {
            "#text": "https://lastfm.freetls.fastly.net/i/u/64s/80851305d15888d28074fe9a3eba851d.png",
            "size": "medium"
          },
          {
            "#text": "https://lastfm.freetls.fastly.net/i/u/174s/80851305d15888d28074fe9a3eba851d.png",
            "size": "large"
          },
          {
            "#text": "https://lastfm.freetls.fastly.net/i/u/300x300/80851305d15888d28074fe9a3eba851d.png",
            "size": "extralarge"
          }
        ]
      },
      {
        "name": "Bitter Suites to Succubi",
        "playcount": 2236265,
        "mbid": "2f4e05fb-2c99-33a9-999d-1f467efee842",
        "url": "https://www.last.fm/music/Cradle+of+Filth/Bitter+Suites+to+Succubi",
        "artist": {
          "name": "Cradle of Filth",
          "mbid": "7e26cbe1-b8f5-4215-af82-e43d5f8ff308",
          "url": "https://www.last.fm/music/Cradle+of+Filth"
        },
        "image": [
          {
            "#text": "https://lastfm.freetls.fastly.net/i/u/34s/3279434a987649d0990472ace5dd455b.png",
            "size": "small"
          },
          {
            "#text": "https://lastfm.freetls.fastly.net/i/u/64s/3279434a987649d0990472ace5dd455b.png",
            "size": "medium"
          },
          {
            "#text": "https://lastfm.freetls.fastly.net/i/u/174s/3279434a987649d0990472ace5dd455b.png",
            "size": "large"
          },
          {
            "#text": "https://lastfm.freetls.fastly.net/i/u/300x300/3279434a987649d0990472ace5dd455b.png",
            "size": "extralarge"
          }
        ]
      },
      {
        "name": "Thornography",
        "playcount": 2528285,
        "mbid": "6a015db2-6343-3e1d-bcbb-d091bb20138c",
        "url": "https://www.last.fm/music/Cradle+of+Filth/Thornography",
        "artist": {
          "name": "Cradle of Filth",
          "mbid": "7e26cbe1-b8f5-4215-af82-e43d5f8ff308",
          "url": "https://www.last.fm/music/Cradle+of+Filth"
        },
        "image": [
          {
            "#text": "https://lastfm.freetls.fastly.net/i/u/34s/dd9d5f95521c44378d057481b4730f86.png",
            "size": "small"
          },
          {
            "#text": "https://lastfm.freetls.fastly.net/i/u/64s/dd9d5f95521c44378d057481b4730f86.png",
            "size": "medium"
          },
          {
            "#text": "https://lastfm.freetls.fastly.net/i/u/174s/dd9d5f95521c44378d057481b4730f86.png",
            "size": "large"
          },
          {
            "#text": "https://lastfm.freetls.fastly.net/i/u/300x300/dd9d5f95521c44378d057481b4730f86.png",
            "size": "extralarge"
          }
        ]
      },
      {
        "name": "Cruelty and the Beast",
        "playcount": 1746510,
        "mbid": "d1a30fef-2178-40bc-a47c-1456f03e782b",
        "url": "https://www.last.fm/music/Cradle+of+Filth/Cruelty+and+the+Beast",
        "artist": {
          "name": "Cradle of Filth",
          "mbid": "7e26cbe1-b8f5-4215-af82-e43d5f8ff308",
          "url": "https://www.last.fm/music/Cradle+of+Filth"
        },
        "image": [
          {
            "#text": "https://lastfm.freetls.fastly.net/i/u/34s/711994ca1ffbcdf02fc5f0d70cf3130b.png",
            "size": "small"
          },
          {
            "#text": "https://lastfm.freetls.fastly.net/i/u/64s/711994ca1ffbcdf02fc5f0d70cf3130b.png",
            "size": "medium"
          },
          {
            "#text": "https://lastfm.freetls.fastly.net/i/u/174s/711994ca1ffbcdf02fc5f0d70cf3130b.png",
            "size": "large"
          },
          {
            "#text": "https://lastfm.freetls.fastly.net/i/u/300x300/711994ca1ffbcdf02fc5f0d70cf3130b.png",
            "size": "extralarge"
          }
        ]
      },
      {
        "name": "Damnation and a Day",
        "playcount": 2269081,
        "mbid": "48f5ed28-ad70-4e9d-aacf-745114b25129",
        "url": "https://www.last.fm/music/Cradle+of+Filth/Damnation+and+a+Day",
        "artist": {
          "name": "Cradle of Filth",
          "mbid": "7e26cbe1-b8f5-4215-af82-e43d5f8ff308",
          "url": "https://www.last.fm/music/Cradle+of+Filth"
        },
        "image": [
          {
            "#text": "https://lastfm.freetls.fastly.net/i/u/34s/994924ef735d4274bb068a55025ad353.png",
            "size": "small"
          },
          {
            "#text": "https://lastfm.freetls.fastly.net/i/u/64s/994924ef735d4274bb068a55025ad353.png",
            "size": "medium"
          },
          {
            "#text": "https://lastfm.freetls.fastly.net/i/u/174s/994924ef735d4274bb068a55025ad353.png",
            "size": "large"
          },
          {
            "#text": "https://lastfm.freetls.fastly.net/i/u/300x300/994924ef735d4274bb068a55025ad353.png",
            "size": "extralarge"
          }
        ]
      },
      {
        "name": "Dusk and Her Embrace",
        "playcount": 1272315,
        "url": "https://www.last.fm/music/Cradle+of+Filth/Dusk+and+Her+Embrace",
        "artist": {
          "name": "Cradle of Filth",
          "mbid": "7e26cbe1-b8f5-4215-af82-e43d5f8ff308",
          "url": "https://www.last.fm/music/Cradle+of+Filth"
        },
        "image": [
          {
            "#text": "https://lastfm.freetls.fastly.net/i/u/34s/e32b472172064b7c0e1836aaf5e3c06a.png",
            "size": "small"
          },
          {
            "#text": "https://lastfm.freetls.fastly.net/i/u/64s/e32b472172064b7c0e1836aaf5e3c06a.png",
            "size": "medium"
          },
          {
            "#text": "https://lastfm.freetls.fastly.net/i/u/174s/e32b472172064b7c0e1836aaf5e3c06a.png",
            "size": "large"
          },
          {
            "#text": "https://lastfm.freetls.fastly.net/i/u/300x300/e32b472172064b7c0e1836aaf5e3c06a.png",
            "size": "extralarge"
          }
        ]
      },
      {
        "name": "The Principle of Evil Made Flesh",
        "playcount": 1162340,
        "mbid": "495410fc-e0fd-3c29-b697-b8a7c312dfba",
        "url": "https://www.last.fm/music/Cradle+of+Filth/The+Principle+of+Evil+Made+Flesh",
        "artist": {
          "name": "Cradle of Filth",
          "mbid": "7e26cbe1-b8f5-4215-af82-e43d5f8ff308",
          "url": "https://www.last.fm/music/Cradle+of+Filth"
        },
        "image": [
          {
            "#text": "https://lastfm.freetls.fastly.net/i/u/34s/179cba0277c538e09a3f90434b589420.png",
            "size": "small"
          },
          {
            "#text": "https://lastfm.freetls.fastly.net/i/u/64s/179cba0277c538e09a3f90434b589420.png",
            "size": "medium"
          },
          {
            "#text": "https://lastfm.freetls.fastly.net/i/u/174s/179cba0277c538e09a3f90434b589420.png",
            "size": "large"
          },
          {
            "#text": "https://lastfm.freetls.fastly.net/i/u/300x300/179cba0277c538e09a3f90434b589420.png",
            "size": "extralarge"
          }
        ]
      },
      {
        "name": "Godspeed on the Devil's Thunder",
        "playcount": 2097943,
        "url": "https://www.last.fm/music/Cradle+of+Filth/Godspeed+on+the+Devil%27s+Thunder",
        "artist": {
          "name": "Cradle of Filth",
          "mbid": "7e26cbe1-b8f5-4215-af82-e43d5f8ff308",
          "url": "https://www.last.fm/music/Cradle+of+Filth"
        },
        "image": [
          {
            "#text": "https://lastfm.freetls.fastly.net/i/u/34s/d300e08abb284241c23604495365e898.png",
            "size": "small"
          },
          {
            "#text": "https://lastfm.freetls.fastly.net/i/u/64s/d300e08abb284241c23604495365e898.png",
            "size": "medium"
          },
          {
            "#text": "https://lastfm.freetls.fastly.net/i/u/174s/d300e08abb284241c23604495365e898.png",
            "size": "large"
          },
          {
            "#text": "https://lastfm.freetls.fastly.net/i/u/300x300/d300e08abb284241c23604495365e898.png",
            "size": "extralarge"
          }
        ]
      },
      {
        "name": "Lovecraft & Witch Hearts",
        "playcount": 533028,
        "mbid": "bc3407f8-a570-3c0a-8ba8-a9a292e2a290",
        "url": "https://www.last.fm/music/Cradle+of+Filth/Lovecraft+&+Witch+Hearts",
        "artist": {
          "name": "Cradle of Filth",
          "mbid": "7e26cbe1-b8f5-4215-af82-e43d5f8ff308",
          "url": "https://www.last.fm/music/Cradle+of+Filth"
        },
        "image": [
          {
            "#text": "https://lastfm.freetls.fastly.net/i/u/34s/727a715e10155771000dbf489af3c4eb.png",
            "size": "small"
          },
          {
            "#text": "https://lastfm.freetls.fastly.net/i/u/64s/727a715e10155771000dbf489af3c4eb.png",
            "size": "medium"
          },
          {
            "#text": "https://lastfm.freetls.fastly.net/i/u/174s/727a715e10155771000dbf489af3c4eb.png",
            "size": "large"
          },
          {
            "#text": "https://lastfm.freetls.fastly.net/i/u/300x300/727a715e10155771000dbf489af3c4eb.png",
            "size": "extralarge"
          }
        ]
      },
      {
        "name": "Nymphetamine special edition",
        "playcount": 372316,
        "url": "https://www.last.fm/music/Cradle+of+Filth/Nymphetamine+special+edition",
        "artist": {
          "name": "Cradle of Filth",
          "mbid": "7e26cbe1-b8f5-4215-af82-e43d5f8ff308",
          "url": "https://www.last.fm/music/Cradle+of+Filth"
        },
        "image": [
          {
            "#text": "https://lastfm.freetls.fastly.net/i/u/34s/76c8d4d7438f4887c8906440ecc33318.png",
            "size": "small"
          },
          {
            "#text": "https://lastfm.freetls.fastly.net/i/u/64s/76c8d4d7438f4887c8906440ecc33318.png",
            "size": "medium"
          },
          {
            "#text": "https://lastfm.freetls.fastly.net/i/u/174s/76c8d4d7438f4887c8906440ecc33318.png",
            "size": "large"
          },
          {
            "#text": "https://lastfm.freetls.fastly.net/i/u/300x300/76c8d4d7438f4887c8906440ecc33318.png",
            "size": "extralarge"
          }
        ]
      },
      {
        "name": "From The Cradle To Enslave",
        "playcount": 406269,
        "mbid": "c2281aef-52b9-3551-90ca-60d9acc5cc0f",
        "url": "https://www.last.fm/music/Cradle+of+Filth/From+The+Cradle+To+Enslave",
        "artist": {
          "name": "Cradle of Filth",
          "mbid": "7e26cbe1-b8f5-4215-af82-e43d5f8ff308",
          "url": "https://www.last.fm/music/Cradle+of+Filth"
        },
        "image": [
          {
            "#text": "https://lastfm.freetls.fastly.net/i/u/34s/7f69c2ff2c1244f5b996335f61f283ac.png",
            "size": "small"
          },
          {
            "#text": "https://lastfm.freetls.fastly.net/i/u/64s/7f69c2ff2c1244f5b996335f61f283ac.png",
            "size": "medium"
          },
          {
            "#text": "https://lastfm.freetls.fastly.net/i/u/174s/7f69c2ff2c1244f5b996335f61f283ac.png",
            "size": "large"
          },
          {
            "#text": "https://lastfm.freetls.fastly.net/i/u/300x300/7f69c2ff2c1244f5b996335f61f283ac.png",
            "size": "extralarge"
          }
        ]
      },
      {
        "name": "Lovecraft and Witch Hearts",
        "playcount": 188180,
        "url": "https://www.last.fm/music/Cradle+of+Filth/Lovecraft+and+Witch+Hearts",
        "artist": {
          "name": "Cradle of Filth",
          "mbid": "7e26cbe1-b8f5-4215-af82-e43d5f8ff308",
          "url": "https://www.last.fm/music/Cradle+of+Filth"
        },
        "image": [
          {
            "#text": "https://lastfm.freetls.fastly.net/i/u/34s/9102422f198744df9a000dc3eb54f69c.png",
            "size": "small"
          },
          {
            "#text": "https://lastfm.freetls.fastly.net/i/u/64s/9102422f198744df9a000dc3eb54f69c.png",
            "size": "medium"
          },
          {
            "#text": "https://lastfm.freetls.fastly.net/i/u/174s/9102422f198744df9a000dc3eb54f69c.png",
            "size": "large"
          },
          {
            "#text": "https://lastfm.freetls.fastly.net/i/u/300x300/9102422f198744df9a000dc3eb54f69c.png",
            "size": "extralarge"
          }
        ]
      },
      {
        "name": "Darkly, Darkly, Venus Aversa",
        "playcount": 1079097,
        "mbid": "e7505693-5eaa-3783-8cb8-9c94868aef8c",
        "url": "https://www.last.fm/music/Cradle+of+Filth/Darkly,+Darkly,+Venus+Aversa",
        "artist": {
          "name": "Cradle of Filth",
          "mbid": "7e26cbe1-b8f5-4215-af82-e43d5f8ff308",
          "url": "https://www.last.fm/music/Cradle+of+Filth"
        },
        "image": [
          {
            "#text": "https://lastfm.freetls.fastly.net/i/u/34s/f80a214099194655a33fa75f5053e11c.png",
            "size": "small"
          },
          {
            "#text": "https://lastfm.freetls.fastly.net/i/u/64s/f80a214099194655a33fa75f5053e11c.png",
            "size": "medium"
          },
          {
            "#text": "https://lastfm.freetls.fastly.net/i/u/174s/f80a214099194655a33fa75f5053e11c.png",
            "size": "large"
          },
          {
            "#text": "https://lastfm.freetls.fastly.net/i/u/300x300/f80a214099194655a33fa75f5053e11c.png",
            "size": "extralarge"
          }
        ]
      },
      {
        "name": "Thornography [Special Edition]",
        "playcount": 219279,
        "url": "https://www.last.fm/music/Cradle+of+Filth/Thornography+%5BSpecial+Edition%5D",
        "artist": {
          "name": "Cradle of Filth",
          "mbid": "7e26cbe1-b8f5-4215-af82-e43d5f8ff308",
          "url": "https://www.last.fm/music/Cradle+of+Filth"
        },
        "image": [
          {
            "#text": "https://lastfm.freetls.fastly.net/i/u/34s/fe29d7a6b15b81d683e726dc5fd69edb.png",
            "size": "small"
          },
          {
            "#text": "https://lastfm.freetls.fastly.net/i/u/64s/fe29d7a6b15b81d683e726dc5fd69edb.png",
            "size": "medium"
          },
          {
            "#text": "https://lastfm.freetls.fastly.net/i/u/174s/fe29d7a6b15b81d683e726dc5fd69edb.png",
            "size": "large"
          },
          {
            "#text": "https://lastfm.freetls.fastly.net/i/u/300x300/fe29d7a6b15b81d683e726dc5fd69edb.png",
            "size": "extralarge"
          }
        ]
      },
      {
        "name": "Live Bait for the Dead",
        "playcount": 387135,
        "mbid": "340898ad-646f-3349-8a8b-b52fc3d6782a",
        "url": "https://www.last.fm/music/Cradle+of+Filth/Live+Bait+for+the+Dead",
        "artist": {
          "name": "Cradle of Filth",
          "mbid": "7e26cbe1-b8f5-4215-af82-e43d5f8ff308",
          "url": "https://www.last.fm/music/Cradle+of+Filth"
        },
        "image": [
          {
            "#text": "https://lastfm.freetls.fastly.net/i/u/34s/49386654ad804496ade500a6e28ff7c8.png",
            "size": "small"
          },
          {
            "#text": "https://lastfm.freetls.fastly.net/i/u/64s/49386654ad804496ade500a6e28ff7c8.png",
            "size": "medium"
          },
          {
            "#text": "https://lastfm.freetls.fastly.net/i/u/174s/49386654ad804496ade500a6e28ff7c8.png",
            "size": "large"
          },
          {
            "#text": "https://lastfm.freetls.fastly.net/i/u/300x300/49386654ad804496ade500a6e28ff7c8.png",
            "size": "extralarge"
          }
        ]
      },
      {
        "name": "From the Cradle to Enslave EP",
        "playcount": 180481,
        "url": "https://www.last.fm/music/Cradle+of+Filth/From+the+Cradle+to+Enslave+EP",
        "artist": {
          "name": "Cradle of Filth",
          "mbid": "7e26cbe1-b8f5-4215-af82-e43d5f8ff308",
          "url": "https://www.last.fm/music/Cradle+of+Filth"
        },
        "image": [
          {
            "#text": "https://lastfm.freetls.fastly.net/i/u/34s/10522fbb34654c17bf7a47af8fe62687.png",
            "size": "small"
          },
          {
            "#text": "https://lastfm.freetls.fastly.net/i/u/64s/10522fbb34654c17bf7a47af8fe62687.png",
            "size": "medium"
          },
          {
            "#text": "https://lastfm.freetls.fastly.net/i/u/174s/10522fbb34654c17bf7a47af8fe62687.png",
            "size": "large"
          },
          {
            "#text": "https://lastfm.freetls.fastly.net/i/u/300x300/10522fbb34654c17bf7a47af8fe62687.png",
            "size": "extralarge"
          }
        ]
      },
      {
        "name": "Hammer of the Witches",
        "playcount": 529290,
        "url": "https://www.last.fm/music/Cradle+of+Filth/Hammer+of+the+Witches",
        "artist": {
          "name": "Cradle of Filth",
          "mbid": "7e26cbe1-b8f5-4215-af82-e43d5f8ff308",
          "url": "https://www.last.fm/music/Cradle+of+Filth"
        },
        "image": [
          {
            "#text": "https://lastfm.freetls.fastly.net/i/u/34s/5628320da3c915f1c028612c27dd8234.png",
            "size": "small"
          },
          {
            "#text": "https://lastfm.freetls.fastly.net/i/u/64s/5628320da3c915f1c028612c27dd8234.png",
            "size": "medium"
          },
          {
            "#text": "https://lastfm.freetls.fastly.net/i/u/174s/5628320da3c915f1c028612c27dd8234.png",
            "size": "large"
          },
          {
            "#text": "https://lastfm.freetls.fastly.net/i/u/300x300/5628320da3c915f1c028612c27dd8234.png",
            "size": "extralarge"
          }
        ]
      },
      {
        "name": "Cryptoriana - The Seductiveness Of Decay",
        "playcount": 335861,
        "url": "https://www.last.fm/music/Cradle+of+Filth/Cryptoriana+-+The+Seductiveness+Of+Decay",
        "artist": {
          "name": "Cradle of Filth",
          "mbid": "7e26cbe1-b8f5-4215-af82-e43d5f8ff308",
          "url": "https://www.last.fm/music/Cradle+of+Filth"
        },
        "image": [
          {
            "#text": "https://lastfm.freetls.fastly.net/i/u/34s/d0a5513f308f40d0526c62bf6783ae67.png",
            "size": "small"
          },
          {
            "#text": "https://lastfm.freetls.fastly.net/i/u/64s/d0a5513f308f40d0526c62bf6783ae67.png",
            "size": "medium"
          },
          {
            "#text": "https://lastfm.freetls.fastly.net/i/u/174s/d0a5513f308f40d0526c62bf6783ae67.png",
            "size": "large"
          },
          {
            "#text": "https://lastfm.freetls.fastly.net/i/u/300x300/d0a5513f308f40d0526c62bf6783ae67.png",
            "size": "extralarge"
          }
        ]
      },
      {
        "name": "Harder, Darker, Faster: Thornography Deluxe",
        "playcount": 380806,
        "mbid": "0bbaf89d-d19d-4f3d-9e98-5adac50f8695",
        "url": "https://www.last.fm/music/Cradle+of+Filth/Harder,+Darker,+Faster:+Thornography+Deluxe",
        "artist": {
          "name": "Cradle of Filth",
          "mbid": "7e26cbe1-b8f5-4215-af82-e43d5f8ff308",
          "url": "https://www.last.fm/music/Cradle+of+Filth"
        },
        "image": [
          {
            "#text": "https://lastfm.freetls.fastly.net/i/u/34s/595cc975076248368240ae51d23423c1.png",
            "size": "small"
          },
          {
            "#text": "https://lastfm.freetls.fastly.net/i/u/64s/595cc975076248368240ae51d23423c1.png",
            "size": "medium"
          },
          {
            "#text": "https://lastfm.freetls.fastly.net/i/u/174s/595cc975076248368240ae51d23423c1.png",
            "size": "large"
          },
          {
            "#text": "https://lastfm.freetls.fastly.net/i/u/300x300/595cc975076248368240ae51d23423c1.png",
            "size": "extralarge"
          }
        ]
      },
      {
        "name": "The Manticore and Other Horrors",
        "playcount": 414076,
        "mbid": "0c2771dd-a562-49a7-a93d-e133e9d221fa",
        "url": "https://www.last.fm/music/Cradle+of+Filth/The+Manticore+and+Other+Horrors",
        "artist": {
          "name": "Cradle of Filth",
          "mbid": "7e26cbe1-b8f5-4215-af82-e43d5f8ff308",
          "url": "https://www.last.fm/music/Cradle+of+Filth"
        },
        "image": [
          {
            "#text": "https://lastfm.freetls.fastly.net/i/u/34s/043e00ca6358459da76082a9a81c8ad1.png",
            "size": "small"
          },
          {
            "#text": "https://lastfm.freetls.fastly.net/i/u/64s/043e00ca6358459da76082a9a81c8ad1.png",
            "size": "medium"
          },
          {
            "#text": "https://lastfm.freetls.fastly.net/i/u/174s/043e00ca6358459da76082a9a81c8ad1.png",
            "size": "large"
          },
          {
            "#text": "https://lastfm.freetls.fastly.net/i/u/300x300/043e00ca6358459da76082a9a81c8ad1.png",
            "size": "extralarge"
          }
        ]
      },
      {
        "name": "Dusk & Her Embrace",
        "playcount": 192180,
        "url": "https://www.last.fm/music/Cradle+of+Filth/Dusk+&+Her+Embrace",
        "artist": {
          "name": "Cradle of Filth",
          "mbid": "7e26cbe1-b8f5-4215-af82-e43d5f8ff308",
          "url": "https://www.last.fm/music/Cradle+of+Filth"
        },
        "image": [
          {
            "#text": "https://lastfm.freetls.fastly.net/i/u/34s/d1b5798134a04aad0f0260a9f734ac28.png",
            "size": "small"
          },
          {
            "#text": "https://lastfm.freetls.fastly.net/i/u/64s/d1b5798134a04aad0f0260a9f734ac28.png",
            "size": "medium"
          },
          {
            "#text": "https://lastfm.freetls.fastly.net/i/u/174s/d1b5798134a04aad0f0260a9f734ac28.png",
            "size": "large"
          },
          {
            "#text": "https://lastfm.freetls.fastly.net/i/u/300x300/d1b5798134a04aad0f0260a9f734ac28.png",
            "size": "extralarge"
          }
        ]
      },
      {
        "name": "The Evil's Bitter Sweet",
        "playcount": 112286,
        "mbid": "95a56db2-5501-4934-9124-6c6d5a12a8be",
        "url": "https://www.last.fm/music/Cradle+of+Filth/The+Evil%27s+Bitter+Sweet",
        "artist": {
          "name": "Cradle of Filth",
          "mbid": "7e26cbe1-b8f5-4215-af82-e43d5f8ff308",
          "url": "https://www.last.fm/music/Cradle+of+Filth"
        },
        "image": [
          {
            "#text": "https://lastfm.freetls.fastly.net/i/u/34s/973a058eab9d4cc29135bfa3773bf882.png",
            "size": "small"
          },
          {
            "#text": "https://lastfm.freetls.fastly.net/i/u/64s/973a058eab9d4cc29135bfa3773bf882.png",
            "size": "medium"
          },
          {
            "#text": "https://lastfm.freetls.fastly.net/i/u/174s/973a058eab9d4cc29135bfa3773bf882.png",
            "size": "large"
          },
          {
            "#text": "https://lastfm.freetls.fastly.net/i/u/300x300/973a058eab9d4cc29135bfa3773bf882.png",
            "size": "extralarge"
          }
        ]
      },
      {
        "name": "Vempire",
        "playcount": 119592,
        "url": "https://www.last.fm/music/Cradle+of+Filth/Vempire",
        "artist": {
          "name": "Cradle of Filth",
          "mbid": "7e26cbe1-b8f5-4215-af82-e43d5f8ff308",
          "url": "https://www.last.fm/music/Cradle+of+Filth"
        },
        "image": [
          {
            "#text": "https://lastfm.freetls.fastly.net/i/u/34s/59f043b24ad7427496ef5592716d9d55.png",
            "size": "small"
          },
          {
            "#text": "https://lastfm.freetls.fastly.net/i/u/64s/59f043b24ad7427496ef5592716d9d55.png",
            "size": "medium"
          },
          {
            "#text": "https://lastfm.freetls.fastly.net/i/u/174s/59f043b24ad7427496ef5592716d9d55.png",
            "size": "large"
          },
          {
            "#text": "https://lastfm.freetls.fastly.net/i/u/300x300/59f043b24ad7427496ef5592716d9d55.png",
            "size": "extralarge"
          }
        ]
      },
      {
        "name": "(null)",
        "playcount": 178541,
        "url": "https://www.last.fm/music/Cradle+of+Filth/(null)",
        "artist": {
          "name": "Cradle of Filth",
          "mbid": "7e26cbe1-b8f5-4215-af82-e43d5f8ff308",
          "url": "https://www.last.fm/music/Cradle+of+Filth"
        },
        "image": [
          {
            "#text": "",
            "size": "small"
          },
          {
            "#text": "",
            "size": "medium"
          },
          {
            "#text": "",
            "size": "large"
          },
          {
            "#text": "",
            "size": "extralarge"
          }
        ]
      },
      {
        "name": "Eleven Burial Masses",
        "playcount": 111450,
        "mbid": "c09b612f-31bb-407e-a9d3-2f6c73604b5e",
        "url": "https://www.last.fm/music/Cradle+of+Filth/Eleven+Burial+Masses",
        "artist": {
          "name": "Cradle of Filth",
          "mbid": "7e26cbe1-b8f5-4215-af82-e43d5f8ff308",
          "url": "https://www.last.fm/music/Cradle+of+Filth"
        },
        "image": [
          {
            "#text": "https://lastfm.freetls.fastly.net/i/u/34s/58b65b8c9477b31d20c77e0d9e80c024.png",
            "size": "small"
          },
          {
            "#text": "https://lastfm.freetls.fastly.net/i/u/64s/58b65b8c9477b31d20c77e0d9e80c024.png",
            "size": "medium"
          },
          {
            "#text": "https://lastfm.freetls.fastly.net/i/u/174s/58b65b8c9477b31d20c77e0d9e80c024.png",
            "size": "large"
          },
          {
            "#text": "https://lastfm.freetls.fastly.net/i/u/300x300/58b65b8c9477b31d20c77e0d9e80c024.png",
            "size": "extralarge"
          }
        ]
      },
      {
        "name": "Total Fucking Darkness",
        "playcount": 66450,
        "mbid": "ba6aa974-4286-4a0e-85f1-cecb6c094b2e",
        "url": "https://www.last.fm/music/Cradle+of+Filth/Total+Fucking+Darkness",
        "artist": {
          "name": "Cradle of Filth",
          "mbid": "7e26cbe1-b8f5-4215-af82-e43d5f8ff308",
          "url": "https://www.last.fm/music/Cradle+of+Filth"
        },
        "image": [
          {
            "#text": "https://lastfm.freetls.fastly.net/i/u/34s/b4c791d6f95840eac0bc64ce5a78c953.png",
            "size": "small"
          },
          {
            "#text": "https://lastfm.freetls.fastly.net/i/u/64s/b4c791d6f95840eac0bc64ce5a78c953.png",
            "size": "medium"
          },
          {
            "#text": "https://lastfm.freetls.fastly.net/i/u/174s/b4c791d6f95840eac0bc64ce5a78c953.png",
            "size": "large"
          },
          {
            "#text": "https://lastfm.freetls.fastly.net/i/u/300x300/b4c791d6f95840eac0bc64ce5a78c953.png",
            "size": "extralarge"
          }
        ]
      },
      {
        "name": "Evermore Darkly",
        "playcount": 99050,
        "mbid": "cfb41172-2836-489f-9f8c-23d2dc923680",
        "url": "https://www.last.fm/music/Cradle+of+Filth/Evermore+Darkly",
        "artist": {
          "name": "Cradle of Filth",
          "mbid": "7e26cbe1-b8f5-4215-af82-e43d5f8ff308",
          "url": "https://www.last.fm/music/Cradle+of+Filth"
        },
        "image": [
          {
            "#text": "https://lastfm.freetls.fastly.net/i/u/34s/ccb04a4a1cbb400b94c222a7395b7d4e.png",
            "size": "small"
          },
          {
            "#text": "https://lastfm.freetls.fastly.net/i/u/64s/ccb04a4a1cbb400b94c222a7395b7d4e.png",
            "size": "medium"
          },
          {
            "#text": "https://lastfm.freetls.fastly.net/i/u/174s/ccb04a4a1cbb400b94c222a7395b7d4e.png",
            "size": "large"
          },
          {
            "#text": "https://lastfm.freetls.fastly.net/i/u/300x300/ccb04a4a1cbb400b94c222a7395b7d4e.png",
            "size": "extralarge"
          }
        ]
      },
      {
        "name": "Sodomizing the Virgin Vamps",
        "playcount": 77279,
        "mbid": "cc8c13ed-65ba-40de-afe4-6099129b1735",
        "url": "https://www.last.fm/music/Cradle+of+Filth/Sodomizing+the+Virgin+Vamps",
        "artist": {
          "name": "Cradle of Filth",
          "mbid": "7e26cbe1-b8f5-4215-af82-e43d5f8ff308",
          "url": "https://www.last.fm/music/Cradle+of+Filth"
        },
        "image": [
          {
            "#text": "https://lastfm.freetls.fastly.net/i/u/34s/53ead556d624cf29293f25d19b27a0a6.png",
            "size": "small"
          },
          {
            "#text": "https://lastfm.freetls.fastly.net/i/u/64s/53ead556d624cf29293f25d19b27a0a6.png",
            "size": "medium"
          },
          {
            "#text": "https://lastfm.freetls.fastly.net/i/u/174s/53ead556d624cf29293f25d19b27a0a6.png",
            "size": "large"
          },
          {
            "#text": "https://lastfm.freetls.fastly.net/i/u/300x300/53ead556d624cf29293f25d19b27a0a6.png",
            "size": "extralarge"
          }
        ]
      },
      {
        "name": "Vempire or Dark Faerytales in Phallustein",
        "playcount": 93958,
        "url": "https://www.last.fm/music/Cradle+of+Filth/Vempire+or+Dark+Faerytales+in+Phallustein",
        "artist": {
          "name": "Cradle of Filth",
          "mbid": "7e26cbe1-b8f5-4215-af82-e43d5f8ff308",
          "url": "https://www.last.fm/music/Cradle+of+Filth"
        },
        "image": [
          {
            "#text": "https://lastfm.freetls.fastly.net/i/u/34s/b936ad385985143dab8dd72c452711f2.png",
            "size": "small"
          },
          {
            "#text": "https://lastfm.freetls.fastly.net/i/u/64s/b936ad385985143dab8dd72c452711f2.png",
            "size": "medium"
          },
          {
            "#text": "https://lastfm.freetls.fastly.net/i/u/174s/b936ad385985143dab8dd72c452711f2.png",
            "size": "large"
          },
          {
            "#text": "https://lastfm.freetls.fastly.net/i/u/300x300/b936ad385985143dab8dd72c452711f2.png",
            "size": "extralarge"
          }
        ]
      },
      {
        "name": "Resident Evil 2 - Apocalypse OST",
        "playcount": 63927,
        "url": "https://www.last.fm/music/Cradle+of+Filth/Resident+Evil+2+-+Apocalypse+OST",
        "artist": {
          "name": "Cradle of Filth",
          "mbid": "7e26cbe1-b8f5-4215-af82-e43d5f8ff308",
          "url": "https://www.last.fm/music/Cradle+of+Filth"
        },
        "image": [
          {
            "#text": "https://lastfm.freetls.fastly.net/i/u/34s/07804bff00f04c53bf0576f7dbb234ea.png",
            "size": "small"
          },
          {
            "#text": "https://lastfm.freetls.fastly.net/i/u/64s/07804bff00f04c53bf0576f7dbb234ea.png",
            "size": "medium"
          },
          {
            "#text": "https://lastfm.freetls.fastly.net/i/u/174s/07804bff00f04c53bf0576f7dbb234ea.png",
            "size": "large"
          },
          {
            "#text": "https://lastfm.freetls.fastly.net/i/u/300x300/07804bff00f04c53bf0576f7dbb234ea.png",
            "size": "extralarge"
          }
        ]
      },
      {
        "name": "Dusk And Her Embrace... The Original Sin",
        "playcount": 72036,
        "url": "https://www.last.fm/music/Cradle+of+Filth/Dusk+And+Her+Embrace...+The+Original+Sin",
        "artist": {
          "name": "Cradle of Filth",
          "mbid": "7e26cbe1-b8f5-4215-af82-e43d5f8ff308",
          "url": "https://www.last.fm/music/Cradle+of+Filth"
        },
        "image": [
          {
            "#text": "https://lastfm.freetls.fastly.net/i/u/34s/6a65e640393ad1650002af342490d80f.png",
            "size": "small"
          },
          {
            "#text": "https://lastfm.freetls.fastly.net/i/u/64s/6a65e640393ad1650002af342490d80f.png",
            "size": "medium"
          },
          {
            "#text": "https://lastfm.freetls.fastly.net/i/u/174s/6a65e640393ad1650002af342490d80f.png",
            "size": "large"
          },
          {
            "#text": "https://lastfm.freetls.fastly.net/i/u/300x300/6a65e640393ad1650002af342490d80f.png",
            "size": "extralarge"
          }
        ]
      },
      {
        "name": "The Very Best Of",
        "playcount": 128897,
        "mbid": "825ad41f-48e4-49dc-804e-a4899960a7c6",
        "url": "https://www.last.fm/music/Cradle+of+Filth/The+Very+Best+Of",
        "artist": {
          "name": "Cradle of Filth",
          "mbid": "7e26cbe1-b8f5-4215-af82-e43d5f8ff308",
          "url": "https://www.last.fm/music/Cradle+of+Filth"
        },
        "image": [
          {
            "#text": "https://lastfm.freetls.fastly.net/i/u/34s/fe3938d7128b4d3394cbe9ef75ac3f8a.png",
            "size": "small"
          },
          {
            "#text": "https://lastfm.freetls.fastly.net/i/u/64s/fe3938d7128b4d3394cbe9ef75ac3f8a.png",
            "size": "medium"
          },
          {
            "#text": "https://lastfm.freetls.fastly.net/i/u/174s/fe3938d7128b4d3394cbe9ef75ac3f8a.png",
            "size": "large"
          },
          {
            "#text": "https://lastfm.freetls.fastly.net/i/u/300x300/fe3938d7128b4d3394cbe9ef75ac3f8a.png",
            "size": "extralarge"
          }
        ]
      },
      {
        "name": "Nymphetamine (disc 2)",
        "playcount": 20533,
        "url": "https://www.last.fm/music/Cradle+of+Filth/Nymphetamine+(disc+2)",
        "artist": {
          "name": "Cradle of Filth",
          "mbid": "7e26cbe1-b8f5-4215-af82-e43d5f8ff308",
          "url": "https://www.last.fm/music/Cradle+of+Filth"
        },
        "image": [
          {
            "#text": "https://lastfm.freetls.fastly.net/i/u/34s/48f74adfdd4640b7abe65b8e9446edc6.png",
            "size": "small"
          },
          {
            "#text": "https://lastfm.freetls.fastly.net/i/u/64s/48f74adfdd4640b7abe65b8e9446edc6.png",
            "size": "medium"
          },
          {
            "#text": "https://lastfm.freetls.fastly.net/i/u/174s/48f74adfdd4640b7abe65b8e9446edc6.png",
            "size": "large"
          },
          {
            "#text": "https://lastfm.freetls.fastly.net/i/u/300x300/48f74adfdd4640b7abe65b8e9446edc6.png",
            "size": "extralarge"
          }
        ]
      },
      {
        "name": "Cruelty and the Beast - Re-Mistressed",
        "playcount": 68607,
        "url": "https://www.last.fm/music/Cradle+of+Filth/Cruelty+and+the+Beast+-+Re-Mistressed",
        "artist": {
          "name": "Cradle of Filth",
          "mbid": "7e26cbe1-b8f5-4215-af82-e43d5f8ff308",
          "url": "https://www.last.fm/music/Cradle+of+Filth"
        },
        "image": [
          {
            "#text": "https://lastfm.freetls.fastly.net/i/u/34s/a3a6d65bfe8fc133ea588aa489d94f97.png",
            "size": "small"
          },
          {
            "#text": "https://lastfm.freetls.fastly.net/i/u/64s/a3a6d65bfe8fc133ea588aa489d94f97.png",
            "size": "medium"
          },
          {
            "#text": "https://lastfm.freetls.fastly.net/i/u/174s/a3a6d65bfe8fc133ea588aa489d94f97.png",
            "size": "large"
          },
          {
            "#text": "https://lastfm.freetls.fastly.net/i/u/300x300/a3a6d65bfe8fc133ea588aa489d94f97.png",
            "size": "extralarge"
          }
        ]
      },
      {
        "name": "Iron Maiden Cover",
        "playcount": 26733,
        "url": "https://www.last.fm/music/Cradle+of+Filth/Iron+Maiden+Cover",
        "artist": {
          "name": "Cradle of Filth",
          "mbid": "7e26cbe1-b8f5-4215-af82-e43d5f8ff308",
          "url": "https://www.last.fm/music/Cradle+of+Filth"
        },
        "image": [
          {
            "#text": "",
            "size": "small"
          },
          {
            "#text": "",
            "size": "medium"
          },
          {
            "#text": "",
            "size": "large"
          },
          {
            "#text": "",
            "size": "extralarge"
          }
        ]
      },
      {
        "name": "Lovecraft & Witch Hearts Disc 2",
        "playcount": 76744,
        "url": "https://www.last.fm/music/Cradle+of+Filth/Lovecraft+&+Witch+Hearts+Disc+2",
        "artist": {
          "name": "Cradle of Filth",
          "mbid": "7e26cbe1-b8f5-4215-af82-e43d5f8ff308",
          "url": "https://www.last.fm/music/Cradle+of+Filth"
        },
        "image": [
          {
            "#text": "https://lastfm.freetls.fastly.net/i/u/34s/3d5e826e3744489cb1e12ea43e502358.png",
            "size": "small"
          },
          {
            "#text": "https://lastfm.freetls.fastly.net/i/u/64s/3d5e826e3744489cb1e12ea43e502358.png",
            "size": "medium"
          },
          {
            "#text": "https://lastfm.freetls.fastly.net/i/u/174s/3d5e826e3744489cb1e12ea43e502358.png",
            "size": "large"
          },
          {
            "#text": "https://lastfm.freetls.fastly.net/i/u/300x300/3d5e826e3744489cb1e12ea43e502358.png",
            "size": "extralarge"
          }
        ]
      },
      {
        "name": "The Manticore and Other Horrors - Extended Claws",
        "playcount": 60418,
        "url": "https://www.last.fm/music/Cradle+of+Filth/The+Manticore+and+Other+Horrors+-+Extended+Claws",
        "artist": {
          "name": "Cradle of Filth",
          "mbid": "7e26cbe1-b8f5-4215-af82-e43d5f8ff308",
          "url": "https://www.last.fm/music/Cradle+of+Filth"
        },
        "image": [
          {
            "#text": "https://lastfm.freetls.fastly.net/i/u/34s/825172c773294bef990495804b428085.png",
            "size": "small"
          },
          {
            "#text": "https://lastfm.freetls.fastly.net/i/u/64s/825172c773294bef990495804b428085.png",
            "size": "medium"
          },
          {
            "#text": "https://lastfm.freetls.fastly.net/i/u/174s/825172c773294bef990495804b428085.png",
            "size": "large"
          },
          {
            "#text": "https://lastfm.freetls.fastly.net/i/u/300x300/825172c773294bef990495804b428085.png",
            "size": "extralarge"
          }
        ]
      },
      {
        "name": "Nymphetamine [2-Disc Special Edition] Disc 1",
        "playcount": 128030,
        "url": "https://www.last.fm/music/Cradle+of+Filth/Nymphetamine+%5B2-Disc+Special+Edition%5D+Disc+1",
        "artist": {
          "name": "Cradle of Filth",
          "mbid": "7e26cbe1-b8f5-4215-af82-e43d5f8ff308",
          "url": "https://www.last.fm/music/Cradle+of+Filth"
        },
        "image": [
          {
            "#text": "https://lastfm.freetls.fastly.net/i/u/34s/754ac384ea8d4770c747c84afb01e99a.png",
            "size": "small"
          },
          {
            "#text": "https://lastfm.freetls.fastly.net/i/u/64s/754ac384ea8d4770c747c84afb01e99a.png",
            "size": "medium"
          },
          {
            "#text": "https://lastfm.freetls.fastly.net/i/u/174s/754ac384ea8d4770c747c84afb01e99a.png",
            "size": "large"
          },
          {
            "#text": "https://lastfm.freetls.fastly.net/i/u/300x300/754ac384ea8d4770c747c84afb01e99a.png",
            "size": "extralarge"
          }
        ]
      },
      {
        "name": "undefined",
        "playcount": 12918,
        "url": "https://www.last.fm/music/Cradle+of+Filth/undefined",
        "artist": {
          "name": "Cradle of Filth",
          "mbid": "7e26cbe1-b8f5-4215-af82-e43d5f8ff308",
          "url": "https://www.last.fm/music/Cradle+of+Filth"
        },
        "image": [
          {
            "#text": "",
            "size": "small"
          },
          {
            "#text": "",
            "size": "medium"
          },
          {
            "#text": "",
            "size": "large"
          },
          {
            "#text": "",
            "size": "extralarge"
          }
        ]
      },
      {
        "name": "Lovecraft & Witch Hearts Disc 1",
        "playcount": 76091,
        "url": "https://www.last.fm/music/Cradle+of+Filth/Lovecraft+&+Witch+Hearts+Disc+1",
        "artist": {
          "name": "Cradle of Filth",
          "mbid": "7e26cbe1-b8f5-4215-af82-e43d5f8ff308",
          "url": "https://www.last.fm/music/Cradle+of+Filth"
        },
        "image": [
          {
            "#text": "https://lastfm.freetls.fastly.net/i/u/34s/19ee9e71a08b42ecb6b2c746e2f60fb4.png",
            "size": "small"
          },
          {
            "#text": "https://lastfm.freetls.fastly.net/i/u/64s/19ee9e71a08b42ecb6b2c746e2f60fb4.png",
            "size": "medium"
          },
          {
            "#text": "https://lastfm.freetls.fastly.net/i/u/174s/19ee9e71a08b42ecb6b2c746e2f60fb4.png",
            "size": "large"
          },
          {
            "#text": "https://lastfm.freetls.fastly.net/i/u/300x300/19ee9e71a08b42ecb6b2c746e2f60fb4.png",
            "size": "extralarge"
          }
        ]
      },
      {
        "name": "Midnight in the Labyrinth",
        "playcount": 71854,
        "mbid": "792cc326-089a-461b-9b95-b245d551fd4f",
        "url": "https://www.last.fm/music/Cradle+of+Filth/Midnight+in+the+Labyrinth",
        "artist": {
          "name": "Cradle of Filth",
          "mbid": "7e26cbe1-b8f5-4215-af82-e43d5f8ff308",
          "url": "https://www.last.fm/music/Cradle+of+Filth"
        },
        "image": [
          {
            "#text": "https://lastfm.freetls.fastly.net/i/u/34s/5cdf505508cd4617b02975fa127f7a36.png",
            "size": "small"
          },
          {
            "#text": "https://lastfm.freetls.fastly.net/i/u/64s/5cdf505508cd4617b02975fa127f7a36.png",
            "size": "medium"
          },
          {
            "#text": "https://lastfm.freetls.fastly.net/i/u/174s/5cdf505508cd4617b02975fa127f7a36.png",
            "size": "large"
          },
          {
            "#text": "https://lastfm.freetls.fastly.net/i/u/300x300/5cdf505508cd4617b02975fa127f7a36.png",
            "size": "extralarge"
          }
        ]
      },
      {
        "name": "Invoking the Unclean",
        "playcount": 33378,
        "mbid": "d3af7d3c-9811-4f48-9595-094a50dc37bb",
        "url": "https://www.last.fm/music/Cradle+of+Filth/Invoking+the+Unclean",
        "artist": {
          "name": "Cradle of Filth",
          "mbid": "7e26cbe1-b8f5-4215-af82-e43d5f8ff308",
          "url": "https://www.last.fm/music/Cradle+of+Filth"
        },
        "image": [
          {
            "#text": "https://lastfm.freetls.fastly.net/i/u/34s/a04c1e94a62d447497c1dd925a2f6997.png",
            "size": "small"
          },
          {
            "#text": "https://lastfm.freetls.fastly.net/i/u/64s/a04c1e94a62d447497c1dd925a2f6997.png",
            "size": "medium"
          },
          {
            "#text": "https://lastfm.freetls.fastly.net/i/u/174s/a04c1e94a62d447497c1dd925a2f6997.png",
            "size": "large"
          },
          {
            "#text": "https://lastfm.freetls.fastly.net/i/u/300x300/a04c1e94a62d447497c1dd925a2f6997.png",
            "size": "extralarge"
          }
        ]
      },
      {
        "name": "Vempire or Dark Fairytales in Phallustein",
        "playcount": 50360,
        "url": "https://www.last.fm/music/Cradle+of+Filth/Vempire+or+Dark+Fairytales+in+Phallustein",
        "artist": {
          "name": "Cradle of Filth",
          "mbid": "7e26cbe1-b8f5-4215-af82-e43d5f8ff308",
          "url": "https://www.last.fm/music/Cradle+of+Filth"
        },
        "image": [
          {
            "#text": "https://lastfm.freetls.fastly.net/i/u/34s/733099f28a154ada91cc65f5f6e59b64.png",
            "size": "small"
          },
          {
            "#text": "https://lastfm.freetls.fastly.net/i/u/64s/733099f28a154ada91cc65f5f6e59b64.png",
            "size": "medium"
          },
          {
            "#text": "https://lastfm.freetls.fastly.net/i/u/174s/733099f28a154ada91cc65f5f6e59b64.png",
            "size": "large"
          },
          {
            "#text": "https://lastfm.freetls.fastly.net/i/u/300x300/733099f28a154ada91cc65f5f6e59b64.png",
            "size": "extralarge"
          }
        ]
      },
      {
        "name": "Cruelty and the Beast (Limited Edition Celtic Cross)",
        "playcount": 71706,
        "url": "https://www.last.fm/music/Cradle+of+Filth/Cruelty+and+the+Beast+(Limited+Edition+Celtic+Cross)",
        "artist": {
          "name": "Cradle of Filth",
          "mbid": "7e26cbe1-b8f5-4215-af82-e43d5f8ff308",
          "url": "https://www.last.fm/music/Cradle+of+Filth"
        },
        "image": [
          {
            "#text": "https://lastfm.freetls.fastly.net/i/u/34s/f4186a9dea1d44f4b7d6127222482e63.png",
            "size": "small"
          },
          {
            "#text": "https://lastfm.freetls.fastly.net/i/u/64s/f4186a9dea1d44f4b7d6127222482e63.png",
            "size": "medium"
          },
          {
            "#text": "https://lastfm.freetls.fastly.net/i/u/174s/f4186a9dea1d44f4b7d6127222482e63.png",
            "size": "large"
          },
          {
            "#text": "https://lastfm.freetls.fastly.net/i/u/300x300/f4186a9dea1d44f4b7d6127222482e63.png",
            "size": "extralarge"
          }
        ]
      },
      {
        "name": "Cruelty And The Beast (Celtic)",
        "playcount": 24286,
        "url": "https://www.last.fm/music/Cradle+of+Filth/Cruelty+And+The+Beast+(Celtic)",
        "artist": {
          "name": "Cradle of Filth",
          "mbid": "7e26cbe1-b8f5-4215-af82-e43d5f8ff308",
          "url": "https://www.last.fm/music/Cradle+of+Filth"
        },
        "image": [
          {
            "#text": "",
            "size": "small"
          },
          {
            "#text": "",
            "size": "medium"
          },
          {
            "#text": "",
            "size": "large"
          },
          {
            "#text": "",
            "size": "extralarge"
          }
        ]
      },
      {
        "name": "Godspeed on the Devils Thunder",
        "playcount": 119550,
        "url": "https://www.last.fm/music/Cradle+of+Filth/Godspeed+on+the+Devils+Thunder",
        "artist": {
          "name": "Cradle of Filth",
          "mbid": "7e26cbe1-b8f5-4215-af82-e43d5f8ff308",
          "url": "https://www.last.fm/music/Cradle+of+Filth"
        },
        "image": [
          {
            "#text": "https://lastfm.freetls.fastly.net/i/u/34s/f7d7321f30997be6766efbea21d36d10.png",
            "size": "small"
          },
          {
            "#text": "https://lastfm.freetls.fastly.net/i/u/64s/f7d7321f30997be6766efbea21d36d10.png",
            "size": "medium"
          },
          {
            "#text": "https://lastfm.freetls.fastly.net/i/u/174s/f7d7321f30997be6766efbea21d36d10.png",
            "size": "large"
          },
          {
            "#text": "https://lastfm.freetls.fastly.net/i/u/300x300/f7d7321f30997be6766efbea21d36d10.png",
            "size": "extralarge"
          }
        ]
      },
      {
        "name": "Lovecraft & Witch Hearts CD1",
        "playcount": 49888,
        "url": "https://www.last.fm/music/Cradle+of+Filth/Lovecraft+&+Witch+Hearts+CD1",
        "artist": {
          "name": "Cradle of Filth",
          "mbid": "7e26cbe1-b8f5-4215-af82-e43d5f8ff308",
          "url": "https://www.last.fm/music/Cradle+of+Filth"
        },
        "image": [
          {
            "#text": "https://lastfm.freetls.fastly.net/i/u/34s/5bbb3c2927964629863dab295b357575.png",
            "size": "small"
          },
          {
            "#text": "https://lastfm.freetls.fastly.net/i/u/64s/5bbb3c2927964629863dab295b357575.png",
            "size": "medium"
          },
          {
            "#text": "https://lastfm.freetls.fastly.net/i/u/174s/5bbb3c2927964629863dab295b357575.png",
            "size": "large"
          },
          {
            "#text": "https://lastfm.freetls.fastly.net/i/u/300x300/5bbb3c2927964629863dab295b357575.png",
            "size": "extralarge"
          }
        ]
      },
      {
        "name": "From The Cradle To Enslave E.P.",
        "playcount": 33377,
        "url": "https://www.last.fm/music/Cradle+of+Filth/From+The+Cradle+To+Enslave+E.P.",
        "artist": {
          "name": "Cradle of Filth",
          "mbid": "7e26cbe1-b8f5-4215-af82-e43d5f8ff308",
          "url": "https://www.last.fm/music/Cradle+of+Filth"
        },
        "image": [
          {
            "#text": "https://lastfm.freetls.fastly.net/i/u/34s/8a5446023df34b3b80eab20ee29e3896.png",
            "size": "small"
          },
          {
            "#text": "https://lastfm.freetls.fastly.net/i/u/64s/8a5446023df34b3b80eab20ee29e3896.png",
            "size": "medium"
          },
          {
            "#text": "https://lastfm.freetls.fastly.net/i/u/174s/8a5446023df34b3b80eab20ee29e3896.png",
            "size": "large"
          },
          {
            "#text": "https://lastfm.freetls.fastly.net/i/u/300x300/8a5446023df34b3b80eab20ee29e3896.png",
            "size": "extralarge"
          }
        ]
      },
      {
        "name": "Heartbreak and Seance",
        "playcount": 14039,
        "url": "https://www.last.fm/music/Cradle+of+Filth/Heartbreak+and+Seance",
        "artist": {
          "name": "Cradle of Filth",
          "mbid": "7e26cbe1-b8f5-4215-af82-e43d5f8ff308",
          "url": "https://www.last.fm/music/Cradle+of+Filth"
        },
        "image": [
          {
            "#text": "https://lastfm.freetls.fastly.net/i/u/34s/87816d0116814235c4e7c6eaa0f71a4c.png",
            "size": "small"
          },
          {
            "#text": "https://lastfm.freetls.fastly.net/i/u/64s/87816d0116814235c4e7c6eaa0f71a4c.png",
            "size": "medium"
          },
          {
            "#text": "https://lastfm.freetls.fastly.net/i/u/174s/87816d0116814235c4e7c6eaa0f71a4c.png",
            "size": "large"
          },
          {
            "#text": "https://lastfm.freetls.fastly.net/i/u/300x300/87816d0116814235c4e7c6eaa0f71a4c.png",
            "size": "extralarge"
          }
        ]
      }
    ],
    "@attr": {
      "artist": "Cradle of Filth",
      "page": "1",
      "perPage": "50",
      "totalPages": "354",
      "total": "17655"
    }
  },
  "createdAt": "2021-01-11T11:48:43.812Z"
}
