{
  "album": {
    "name": "Hate Forest / Legion of Doom (Split)",
    "artist": "Hate Forest",
    "url": "https://www.last.fm/music/Hate+Forest/Hate+Forest+%2F+Legion+of+Doom+(Split)",
    "image": [
      {
        "#text": "https://lastfm.freetls.fastly.net/i/u/34s/135619329c1249618f67cad201bdb6ca.png",
        "size": "small"
      },
      {
        "#text": "https://lastfm.freetls.fastly.net/i/u/64s/135619329c1249618f67cad201bdb6ca.png",
        "size": "medium"
      },
      {
        "#text": "https://lastfm.freetls.fastly.net/i/u/174s/135619329c1249618f67cad201bdb6ca.png",
        "size": "large"
      },
      {
        "#text": "https://lastfm.freetls.fastly.net/i/u/300x300/135619329c1249618f67cad201bdb6ca.png",
        "size": "extralarge"
      },
      {
        "#text": "https://lastfm.freetls.fastly.net/i/u/300x300/135619329c1249618f67cad201bdb6ca.png",
        "size": "mega"
      },
      {
        "#text": "https://lastfm.freetls.fastly.net/i/u/300x300/135619329c1249618f67cad201bdb6ca.png",
        "size": ""
      }
    ],
    "listeners": "28",
    "playcount": "66",
    "tracks": {
      "track": []
    },
    "tags": {
      "tag": []
    }
  },
  "createdAt": "2021-01-11T13:03:14.879Z"
}
