{
  "album": {
    "name": "Permafrost",
    "artist": "Countess",
    "mbid": "e22abf56-e785-4815-b8ae-52001d2fd731",
    "url": "https://www.last.fm/music/Countess/Permafrost",
    "image": [
      {
        "#text": "https://lastfm.freetls.fastly.net/i/u/34s/d8156f8bac614714b7e892d4c43348db.png",
        "size": "small"
      },
      {
        "#text": "https://lastfm.freetls.fastly.net/i/u/64s/d8156f8bac614714b7e892d4c43348db.png",
        "size": "medium"
      },
      {
        "#text": "https://lastfm.freetls.fastly.net/i/u/174s/d8156f8bac614714b7e892d4c43348db.png",
        "size": "large"
      },
      {
        "#text": "https://lastfm.freetls.fastly.net/i/u/300x300/d8156f8bac614714b7e892d4c43348db.png",
        "size": "extralarge"
      },
      {
        "#text": "https://lastfm.freetls.fastly.net/i/u/300x300/d8156f8bac614714b7e892d4c43348db.png",
        "size": "mega"
      },
      {
        "#text": "https://lastfm.freetls.fastly.net/i/u/300x300/d8156f8bac614714b7e892d4c43348db.png",
        "size": ""
      }
    ],
    "listeners": "207",
    "playcount": "1265",
    "tracks": {
      "track": [
        {
          "name": "Black Duncans Ride Over Highland",
          "url": "https://www.last.fm/music/Countess/_/Black+Duncans+Ride+Over+Highland",
          "duration": "790",
          "@attr": {
            "rank": "1"
          },
          "streamable": {
            "#text": "0",
            "fulltrack": "0"
          },
          "artist": {
            "name": "Countess",
            "mbid": "35f55b53-1017-4969-b48e-92c079c12b44",
            "url": "https://www.last.fm/music/Countess"
          }
        },
        {
          "name": "A Fine Night To Fight",
          "url": "https://www.last.fm/music/Countess/_/A+Fine+Night+To+Fight",
          "duration": "338",
          "@attr": {
            "rank": "2"
          },
          "streamable": {
            "#text": "0",
            "fulltrack": "0"
          },
          "artist": {
            "name": "Countess",
            "mbid": "35f55b53-1017-4969-b48e-92c079c12b44",
            "url": "https://www.last.fm/music/Countess"
          }
        },
        {
          "name": "Howling At The Moon",
          "url": "https://www.last.fm/music/Countess/_/Howling+At+The+Moon",
          "duration": "496",
          "@attr": {
            "rank": "3"
          },
          "streamable": {
            "#text": "0",
            "fulltrack": "0"
          },
          "artist": {
            "name": "Countess",
            "mbid": "35f55b53-1017-4969-b48e-92c079c12b44",
            "url": "https://www.last.fm/music/Countess"
          }
        },
        {
          "name": "Knights Of Baphomet",
          "url": "https://www.last.fm/music/Countess/_/Knights+Of+Baphomet",
          "duration": "296",
          "@attr": {
            "rank": "4"
          },
          "streamable": {
            "#text": "0",
            "fulltrack": "0"
          },
          "artist": {
            "name": "Countess",
            "mbid": "35f55b53-1017-4969-b48e-92c079c12b44",
            "url": "https://www.last.fm/music/Countess"
          }
        },
        {
          "name": "The Return of Darkness and Evil",
          "url": "https://www.last.fm/music/Countess/_/The+Return+of+Darkness+and+Evil",
          "duration": "222",
          "@attr": {
            "rank": "5"
          },
          "streamable": {
            "#text": "0",
            "fulltrack": "0"
          },
          "artist": {
            "name": "Countess",
            "mbid": "35f55b53-1017-4969-b48e-92c079c12b44",
            "url": "https://www.last.fm/music/Countess"
          }
        }
      ]
    },
    "tags": {
      "tag": []
    }
  },
  "createdAt": "2021-01-11T15:08:32.835Z"
}
