{
  "album": {
    "name": "Maximum Metal Vol. 161",
    "artist": "Dornenreich",
    "url": "https://www.last.fm/music/Dornenreich/Maximum+Metal+Vol.+161",
    "image": [
      {
        "#text": "",
        "size": "small"
      },
      {
        "#text": "",
        "size": "medium"
      },
      {
        "#text": "",
        "size": "large"
      },
      {
        "#text": "",
        "size": "extralarge"
      },
      {
        "#text": "",
        "size": "mega"
      },
      {
        "#text": "",
        "size": ""
      }
    ],
    "listeners": "91",
    "playcount": "352",
    "tracks": {
      "track": []
    },
    "tags": {
      "tag": []
    }
  },
  "createdAt": "2021-01-11T12:26:51.984Z"
}
