{
  "album": {
    "name": "Foulest Semen of A Sheltered Elite Vinyl",
    "artist": "The Ruins of Beverast",
    "url": "https://www.last.fm/music/The+Ruins+of+Beverast/Foulest+Semen+of+A+Sheltered+Elite+Vinyl",
    "image": [
      {
        "#text": "https://lastfm.freetls.fastly.net/i/u/34s/9515c9f4fdac402b89afee4e51d510fb.png",
        "size": "small"
      },
      {
        "#text": "https://lastfm.freetls.fastly.net/i/u/64s/9515c9f4fdac402b89afee4e51d510fb.png",
        "size": "medium"
      },
      {
        "#text": "https://lastfm.freetls.fastly.net/i/u/174s/9515c9f4fdac402b89afee4e51d510fb.png",
        "size": "large"
      },
      {
        "#text": "https://lastfm.freetls.fastly.net/i/u/300x300/9515c9f4fdac402b89afee4e51d510fb.png",
        "size": "extralarge"
      },
      {
        "#text": "https://lastfm.freetls.fastly.net/i/u/300x300/9515c9f4fdac402b89afee4e51d510fb.png",
        "size": "mega"
      },
      {
        "#text": "https://lastfm.freetls.fastly.net/i/u/300x300/9515c9f4fdac402b89afee4e51d510fb.png",
        "size": ""
      }
    ],
    "listeners": "409",
    "playcount": "12281",
    "tracks": {
      "track": []
    },
    "tags": {
      "tag": []
    }
  },
  "createdAt": "2021-01-11T12:34:42.269Z"
}
