{
  "toptags": {
    "tag": [
      {
        "count": 100,
        "name": "black metal",
        "url": "https://www.last.fm/tag/black+metal"
      },
      {
        "count": 34,
        "name": "2010",
        "url": "https://www.last.fm/tag/2010"
      },
      {
        "count": 34,
        "name": "Post-Metal",
        "url": "https://www.last.fm/tag/Post-Metal"
      },
      {
        "count": 34,
        "name": "Post-Black Metal",
        "url": "https://www.last.fm/tag/Post-Black+Metal"
      },
      {
        "count": 17,
        "name": "metal",
        "url": "https://www.last.fm/tag/metal"
      },
      {
        "count": 17,
        "name": "favorite albums",
        "url": "https://www.last.fm/tag/favorite+albums"
      },
      {
        "count": 17,
        "name": "best of 2010",
        "url": "https://www.last.fm/tag/best+of+2010"
      },
      {
        "count": 17,
        "name": "sludge metal",
        "url": "https://www.last.fm/tag/sludge+metal"
      },
      {
        "count": 17,
        "name": "the best",
        "url": "https://www.last.fm/tag/the+best"
      },
      {
        "count": 17,
        "name": "favorite album",
        "url": "https://www.last.fm/tag/favorite+album"
      },
      {
        "count": 17,
        "name": "sludge black metal",
        "url": "https://www.last.fm/tag/sludge+black+metal"
      },
      {
        "count": 17,
        "name": "headbangers ball",
        "url": "https://www.last.fm/tag/headbangers+ball"
      },
      {
        "count": 17,
        "name": "vinyl i own",
        "url": "https://www.last.fm/tag/vinyl+i+own"
      },
      {
        "count": 17,
        "name": "metal2010",
        "url": "https://www.last.fm/tag/metal2010"
      }
    ],
    "@attr": {
      "artist": "Twilight",
      "album": "Monument to Time End"
    }
  },
  "createdAt": "2021-01-11T13:47:53.242Z"
}
